kiera/_init_.py
kiera/main.py
kiera-0.0.19.dist-info/entry_points.txt
kiera-0.0.19.dist-info/WHEEL
kiera-0.0.19.dist-info/METADATA
kiera-0.0.19.dist-info/RECORD
